enapter/__init__.py
enapter/__main__.py
enapter/py.typed
enapter/async_/__init__.py
enapter/async_/generator.py
enapter/async_/routine.py
enapter/cli/__init__.py
enapter/cli/app.py
enapter/cli/command.py
enapter/cli/subparsers.py
enapter/cli/http/__init__.py
enapter/cli/http/command.py
enapter/cli/http/api/__init__.py
enapter/cli/http/api/blueprint_command.py
enapter/cli/http/api/blueprint_download_command.py
enapter/cli/http/api/blueprint_get_command.py
enapter/cli/http/api/blueprint_upload_command.py
enapter/cli/http/api/blueprint_validate_command.py
enapter/cli/http/api/command.py
enapter/cli/http/api/command_arguments.py
enapter/cli/http/api/command_command.py
enapter/cli/http/api/command_create_execution_command.py
enapter/cli/http/api/command_execute_command.py
enapter/cli/http/api/command_get_execution_command.py
enapter/cli/http/api/command_list_executions_command.py
enapter/cli/http/api/device_assign_blueprint_command.py
enapter/cli/http/api/device_command.py
enapter/cli/http/api/device_create_lua_command.py
enapter/cli/http/api/device_create_standalone_command.py
enapter/cli/http/api/device_create_vucm_command.py
enapter/cli/http/api/device_delete_command.py
enapter/cli/http/api/device_generate_communication_config_command.py
enapter/cli/http/api/device_get_command.py
enapter/cli/http/api/device_list_command.py
enapter/cli/http/api/device_update_command.py
enapter/cli/http/api/site_command.py
enapter/cli/http/api/site_create_command.py
enapter/cli/http/api/site_delete_command.py
enapter/cli/http/api/site_get_command.py
enapter/cli/http/api/site_list_command.py
enapter/cli/http/api/site_location.py
enapter/cli/http/api/site_update_command.py
enapter/cli/http/api/telemetry_command.py
enapter/cli/http/api/telemetry_latest_command.py
enapter/cli/http/api/telemetry_timeseries_command.py
enapter/http/__init__.py
enapter/http/api/__init__.py
enapter/http/api/client.py
enapter/http/api/config.py
enapter/http/api/errors.py
enapter/http/api/blueprints/__init__.py
enapter-0.14.4.dist-info/METADATA
enapter-0.14.4.dist-info/WHEEL
enapter-0.14.4.dist-info/top_level.txt
enapter-0.14.4.dist-info/RECORD
