Metadata-Version: 2.4
Name: enapter
Version: 0.14.4
Summary: Enapter Python SDK
Home-page: https://github.com/Enapter/python-sdk
Author: Roman Novatorov
Author-email: rnovatorov@enapter.com
Requires-Dist: aiomqtt==2.4.*
Requires-Dist: dnspython==2.8.*
Requires-Dist: json-log-formatter==1.1.*
Requires-Dist: httpx==0.28.*
Dynamic: author
Dynamic: author-email
Dynamic: description
Dynamic: description-content-type
Dynamic: home-page
Dynamic: requires-dist
Dynamic: summary
